text_patch/__init__.py
text_patch/dict/no_change.example.dict.txt
text_patch/dict/normailze.example.dict.txt
text_patch/processor.py
text_patch-0.1.0.dist-info/WHEEL
text_patch-0.1.0.dist-info/METADATA
text_patch-0.1.0.dist-info/RECORD
