Metadata-Version: 2.1
Name: text-patch
Version: 0.1.0
Summary: 
Author: Philip Huang
Author-email: p208p2002@gmail.com
Requires-Python: >=3.8,<4.0
Classifier: Programming Language :: Python :: 3
Classifier: Programming Language :: Python :: 3.10
Classifier: Programming Language :: Python :: 3.8
Classifier: Programming Language :: Python :: 3.9
Requires-Dist: edit-distance (>=1.0.4,<2.0.0)
